sark/__init__.py
sark/codeblock.py
sark/core.py
sark/data.py
sark/debug.py
sark/enum.py
sark/exceptions.py
sark/graph.py
sark/ipython.py
sark/plumbing.py
sark/qt.py
sark/structure.py
sark/ui.py
sark/code/__init__.py
sark/code/base.py
sark/code/function.py
sark/code/instruction.py
sark/code/intel.py
sark/code/line.py
sark/code/segment.py
sark/code/switch.py
sark/code/xref.py
sark-9.0.0.dist-info/METADATA
sark-9.0.0.dist-info/WHEEL
sark-9.0.0.dist-info/licenses/AUTHORS.rst
sark-9.0.0.dist-info/licenses/LICENSE
sark-9.0.0.dist-info/RECORD
