Metadata-Version: 2.4
Name: sark
Version: 9.0.0
Summary: IDA Scripting Library
Project-URL: Homepage, https://github.com/tmr232/Sark
Author: Tamir Bahar
License-Expression: MIT
License-File: AUTHORS.rst
License-File: LICENSE
Requires-Dist: networkx>=2.0.0
Requires-Dist: wrapt
Provides-Extra: dev
Requires-Dist: approvaltests>=10.1.0; extra == 'dev'
Requires-Dist: keystone-engine==0.9.2; extra == 'dev'
